MANIFEST.in
README.rst
RELEASE-VERSION
git_version.py
setup.cfg
setup.py
ev3dev2/__init__.py
ev3dev2/auto.py
ev3dev2/button.py
ev3dev2/display.py
ev3dev2/led.py
ev3dev2/motor.py
ev3dev2/port.py
ev3dev2/power.py
ev3dev2/sound.py
ev3dev2/version.py
ev3dev2/_platform/__init__.py
ev3dev2/_platform/brickpi.py
ev3dev2/_platform/brickpi3.py
ev3dev2/_platform/ev3.py
ev3dev2/_platform/evb.py
ev3dev2/_platform/fake.py
ev3dev2/_platform/pistorms.py
ev3dev2/control/GyroBalancer.py
ev3dev2/control/__init__.py
ev3dev2/control/rc_tank.py
ev3dev2/control/webserver.py
ev3dev2/fonts/__init__.py
ev3dev2/sensor/__init__.py
ev3dev2/sensor/lego.py
python_ev3dev2.egg-info/PKG-INFO
python_ev3dev2.egg-info/SOURCES.txt
python_ev3dev2.egg-info/dependency_links.txt
python_ev3dev2.egg-info/requires.txt
python_ev3dev2.egg-info/top_level.txt