Metadata-Version: 2.1
Name: python-ev3dev2
Version: 2.0.0b2
Summary: v2.x Python language bindings for ev3dev
Home-page: https://github.com/ev3dev/ev3dev-lang-python
Author: ev3dev Python team
Author-email: python-team@ev3dev.org
License: MIT
Platform: UNKNOWN
